foo_param/__init__.py
foo_param/core.py
foo_param/utils.py
foo_param/tests/__init__.py
foo_param/tests/test_core.py
foo_param/tests/test_utils.py
foo_param-0.1.dist-info/LICENSE
foo_param-0.1.dist-info/METADATA
foo_param-0.1.dist-info/WHEEL
foo_param-0.1.dist-info/entry_points.txt
foo_param-0.1.dist-info/top_level.txt
foo_param-0.1.dist-info/RECORD
